mkeio/__init__.py
mkeio/analog.py
mkeio/audio.py
mkeio/ble.py
mkeio/communication.py
mkeio/device.py
mkeio/dht11.py
mkeio/digital.py
mkeio/lcd.py
mkeio/motor.py
mkeio/pwm.py
mkeio/robot.py
mkeio/rtc.py
mkeio/servo.py
mkeio/sonic.py
mkeio-0.1.8.dist-info/LICENSE
mkeio-0.1.8.dist-info/METADATA
mkeio-0.1.8.dist-info/WHEEL
mkeio-0.1.8.dist-info/top_level.txt
mkeio-0.1.8.dist-info/RECORD
